LocalitySensitiveHashing-1.0.html
MANIFEST.in
Makefile
README
setup.py
Examples/Clustering_with_LSH_with_sample_based_merging.py
Examples/Clustering_with_LSH_with_set_based_merging.py
Examples/LSH_basic_for_demonstrating_nearest_neighbors.py
Examples/README
Examples/data_for_lsh.csv
Examples/gen_data.py
LocalitySensitiveHashing/LocalitySensitiveHashing.py
LocalitySensitiveHashing/__init__.py
LocalitySensitiveHashing.egg-info/PKG-INFO
LocalitySensitiveHashing.egg-info/SOURCES.txt
LocalitySensitiveHashing.egg-info/dependency_links.txt
LocalitySensitiveHashing.egg-info/top_level.txt
TestLSH/LocalitySensitiveHashing.py
TestLSH/Test.py
TestLSH/TestHashStoreInitialization.py
TestLSH/TestLSHDataExtraction.py
TestLSH/data_for_lsh.csv