Metadata-Version: 1.1
Name: LocalitySensitiveHashing
Version: 1.0
Summary: A Python implementation of Locality Sensitive Hashing for finding nearest neighbors and clusters in multidimensional numerical data
Home-page: https://engineering.purdue.edu/kak/distLSH/LocalitySensitiveHashing-1.0.html
Author: Avinash Kak
Author-email: kak@purdue.edu
License: Python Software Foundation License
Download-URL: https://engineering.purdue.edu/kak/distLSH/LocalitySensitiveHashing-1.0.tar.gz#md5=a59feac7509d8e3f323d170d470583a2
Keywords: locality sensitive hashing,nearest neighbor calculation,hashing with hyperplanes,clustering
Platform: All platforms
Classifier: Topic :: Utilities
Classifier: Programming Language :: Python :: 2.7
Classifier: Programming Language :: Python :: 3.5
